AUTHORS.rst
CONTRIBUTING.rst
HISTORY.rst
LICENSE
MANIFEST.in
README.rst
setup.cfg
setup.py
docs/Makefile
docs/authors.rst
docs/conf.py
docs/contributing.rst
docs/history.rst
docs/index.rst
docs/installation.rst
docs/make.bat
docs/readme.rst
docs/usage.rst
hellosagemaker_2020/__init__.py
hellosagemaker_2020/cli.py
hellosagemaker_2020/hellosagemaker_2020.py
hellosagemaker_2020.egg-info/PKG-INFO
hellosagemaker_2020.egg-info/SOURCES.txt
hellosagemaker_2020.egg-info/dependency_links.txt
hellosagemaker_2020.egg-info/entry_points.txt
hellosagemaker_2020.egg-info/not-zip-safe
hellosagemaker_2020.egg-info/requires.txt
hellosagemaker_2020.egg-info/top_level.txt
tests/__init__.py
tests/test_hellosagemaker_2020.py